setup.py
cheat/__init__.py
cheat/app.py
cheat/sheet.py
cheat/sheets.py
cheat/utils.py
cheat.egg-info/PKG-INFO
cheat.egg-info/SOURCES.txt
cheat.egg-info/dependency_links.txt
cheat.egg-info/entry_points.txt
cheat.egg-info/requires.txt
cheat.egg-info/top_level.txt
cheat/cheatsheets/__init__.py
cheat/test/__init__.py