Metadata-Version: 1.0
Name: cheat
Version: 2.1.17
Summary: cheat allows you to create and view interactive cheatsheets on the command-line
Home-page: https://github.com/chrisallenlane/cheat
Author: Chris Lane
Author-email: chris@chris-allen-lane.com
License: GPL3
Platform: UNKNOWN
